indexpy/__init__.py
indexpy/__main__.py
indexpy/__version__.py
indexpy/applications.py
indexpy/cli.py
indexpy/concurrency.py
indexpy/debug.py
indexpy/exceptions.py
indexpy/middlewares/__init__.py
indexpy/middlewares/cors.py
indexpy/openapi/__init__.py
indexpy/openapi/application.py
indexpy/openapi/extra_docs.py
indexpy/openapi/schema.py
indexpy/openapi/specification.py
indexpy/openapi/templates/rapidoc.html
indexpy/openapi/templates/redoc.html
indexpy/openapi/templates/swagger.html
indexpy/openapi/types.py
indexpy/parameters/__init__.py
indexpy/parameters/field_functions.py
indexpy/parameters/fields.py
indexpy/py.typed
indexpy/requests.py
indexpy/responses.py
indexpy/routing/__init__.py
indexpy/routing/commands.py
indexpy/routing/extensions/__init__.py
indexpy/routing/extensions/file.py
indexpy/routing/extensions/multimethod.py
indexpy/routing/routers.py
indexpy/routing/routes.py
indexpy/routing/tree.py
indexpy/status.py
indexpy/templates.py
indexpy/utils/__init__.py
indexpy/utils/contextvars.py
indexpy/utils/contextvars.pyi
indexpy/utils/importer.py
indexpy/utils/inspect.py
indexpy/utils/objects.py
indexpy/utils/pipe.py
indexpy/utils/register.py
indexpy/utils/state.py
indexpy/views.py
index_py-0.21.16.dist-info/LICENSE
index_py-0.21.16.dist-info/METADATA
index_py-0.21.16.dist-info/WHEEL
index_py-0.21.16.dist-info/entry_points.txt
index_py-0.21.16.dist-info/RECORD
