Metadata-Version: 2.1
Name: index.py
Version: 0.21.16
Summary: An easy-to-use high-performance asynchronous web framework.
Home-page: https://github.com/abersheeran/index.py
License: Apache-2.0
Author: abersheeran
Author-email: me@abersheeran.com
Requires-Python: >=3.7,<4.0
Classifier: License :: OSI Approved :: Apache Software License
Classifier: Programming Language :: Python :: 3
Classifier: Programming Language :: Python :: 3.7
Classifier: Programming Language :: Python :: 3.8
Classifier: Programming Language :: Python :: 3.9
Classifier: Programming Language :: Python :: 3.10
Classifier: Programming Language :: Python :: 3.11
Classifier: Programming Language :: Python :: Implementation :: CPython
Provides-Extra: cli
Provides-Extra: docs
Requires-Dist: baize (>=0.15.0,<1.0.0)
Requires-Dist: click (>=8.0,<9.0) ; extra == "cli"
Requires-Dist: pydantic (>=1.8,<2.0)
Requires-Dist: typing-extensions (>=3.10.0)
Project-URL: Documentation, https://index-py.abersheeran.com/
Project-URL: Repository, https://github.com/abersheeran/index.py
